freq_used/__init__.py
freq_used/logging_utils.py
freq_used/mydu.py
freq_used/plotting.py
freq_used/google/__init__.py
freq_used/google/contacts/__init__.py
freq_used/google/contacts/utils.py
freq_used-0.28.dist-info/LICENSE
freq_used-0.28.dist-info/METADATA
freq_used-0.28.dist-info/WHEEL
freq_used-0.28.dist-info/entry_points.txt
freq_used-0.28.dist-info/top_level.txt
freq_used-0.28.dist-info/RECORD
