Metadata-Version: 2.1
Name: freq_used
Version: 0.28
Summary: Frequently used code pieces
Home-page: https://github.com/sungheeyun/FrequentlyUsed
Author: Sunghee Yun
Author-email: sunghee.yun@gmail.com
Classifier: Programming Language :: Python :: 3
Classifier: License :: OSI Approved :: MIT License
Classifier: Operating System :: OS Independent
License-File: LICENSE
